{
	"class" : {
		 },
	"instance" : {
		"parserClass" : "11/16/2016 19:01:21",
		"testComment" : "11/16/2016 19:01:21",
		"testDocument" : "11/16/2016 19:01:21",
		"testElement" : "11/16/2016 19:01:21",
		"testElementEmpty" : "11/16/2016 19:01:21",
		"testElementMalformedExtraClose" : "11/16/2016 19:01:21",
		"testElementMalformedUnclosed" : "11/16/2016 19:01:21",
		"testElementMalformedWrongClose" : "11/16/2016 19:01:21",
		"testElementNested" : "11/16/2016 19:01:21",
		"testJavascript" : "11/16/2016 19:01:21",
		"testJavascriptWithString" : "11/16/2016 19:01:21",
		"testStructuredDocument" : "11/16/2016 19:01:21",
		"testStructuredDocumentSimple" : "JanKurs 12/26/2016 19:01",
		"testStructuredDocumentWithDoctype" : "JanKurs 12/26/2016 19:01",
		"testText" : "11/16/2016 19:01:21" } }
