{
	"class" : {
		 },
	"instance" : {
		"buffer" : "12/5/2016 22:12:51",
		"buffer:" : "12/5/2016 22:12:51",
		"contextMemento" : "12/5/2016 22:12:51",
		"contextMemento:" : "12/5/2016 22:12:51",
		"furthestPosition" : "12/5/2016 22:12:51",
		"furthestPosition:" : "12/5/2016 22:12:51",
		"isPromise" : "12/5/2016 22:12:51",
		"parser" : "12/5/2016 22:12:51",
		"parser:" : "12/5/2016 22:12:51",
		"position" : "12/5/2016 22:12:51",
		"position:" : "12/5/2016 22:12:51",
		"resolveFor:in:" : "12/5/2016 22:12:51" } }
