{
	"instance" : {
		"asPetitStream" : " 4/17/2018 07:53:02",
		"initialize" : " 4/17/2018 07:53:02",
		"contents" : " 4/17/2018 07:53:02",
		"asPetit2Context" : " 4/17/2018 07:53:02",
		"newToken:from:to:" : " 4/17/2018 07:53:02",
		"bufferSize" : " 4/17/2018 07:53:02",
		"atEnd:" : " 4/17/2018 07:53:02",
		"reset" : " 4/17/2018 07:53:02",
		"uncheckedNext" : " 4/17/2018 07:53:02",
		"upToPosition:" : " 4/17/2018 07:53:02",
		"copyFrom:to:" : " 4/17/2018 07:53:02",
		"isBuffered" : " 4/17/2018 07:53:02",
		"buffer" : " 4/17/2018 07:53:02",
		"initializeForSize:" : " 4/17/2018 07:53:02",
		"atPosition:" : " 4/17/2018 07:53:02",
		"printOn:position:" : " 4/17/2018 07:53:02",
		"asPetit2Stream" : " 4/17/2018 07:53:02",
		"last" : " 4/17/2018 07:53:02",
		"stream:" : " 4/17/2018 07:53:02"
	},
	"class" : {
		"new" : " 4/17/2018 07:53:02",
		"on:bufferSize:" : " 4/17/2018 07:53:02",
		"on:" : " 4/17/2018 07:53:02"
	}
}