{
	"instance" : {
		"start" : " 4/17/2018 07:53:02",
		"result" : " 4/17/2018 07:53:02",
		"initialize" : " 4/17/2018 07:53:02",
		"findContextContents" : " 4/17/2018 07:53:02",
		"allResults" : " 4/17/2018 07:53:02",
		"contents" : " 4/17/2018 07:53:02",
		"start:" : " 4/17/2018 07:53:02",
		"parser" : " 4/17/2018 07:53:02",
		"context" : " 4/17/2018 07:53:02",
		"invocationEntry" : " 4/17/2018 07:53:02",
		"findContext" : " 4/17/2018 07:53:02",
		"allResultsTo:" : " 4/17/2018 07:53:02",
		"furthestPosition:" : " 4/17/2018 07:53:02",
		"startStopInterval" : " 4/17/2018 07:53:02",
		"formattedText" : " 4/17/2018 07:53:02",
		"stop" : " 4/17/2018 07:53:02",
		"context:" : " 4/17/2018 07:53:02",
		"parent:" : " 4/17/2018 07:53:02",
		"children" : " 4/17/2018 07:53:02",
		"parser:" : " 4/17/2018 07:53:02",
		"stop:" : " 4/17/2018 07:53:02",
		"steps" : " 4/17/2018 07:53:02",
		"invocationEntry:" : " 4/17/2018 07:53:02",
		"debugResult" : " 4/17/2018 07:53:02",
		"children:" : " 4/17/2018 07:53:02",
		"furthestPosition" : " 4/17/2018 07:53:02",
		"printOn:" : " 4/17/2018 07:53:02",
		"result:" : " 4/17/2018 07:53:02",
		"asEventsMorph" : " 4/17/2018 07:53:02",
		"parent" : " 4/17/2018 07:53:02",
		"isBiggestChild" : " 4/17/2018 07:53:02"
	},
	"class" : { }
}