{
	"instance" : {
		"visitFlatten:" : " 10/30/2016 18:26:47",
		"initialize" : " 10/30/2016 18:26:47",
		"visitOptional:" : " 10/30/2016 18:26:47",
		"visitPP2Node:" : " 10/30/2016 18:26:47",
		"visitAdaptable:" : " 10/30/2016 18:26:47",
		"visitPush:" : "JanKurs 11/1/2016 17:34",
		"visitMatch:" : "JanKurs 11/1/2016 17:33",
		"visitNonEpsilon:" : " 10/30/2016 18:26:47",
		"nextSets" : " 10/30/2016 18:26:47",
		"visitChildrenOf:" : " 10/30/2016 18:26:47",
		"nextSetFor:" : " 10/30/2016 18:26:47",
		"visitPossesiveRepeating:" : " 10/30/2016 18:26:47",
		"parentNextSet" : " 10/30/2016 18:26:47",
		"visitSequence:" : " 10/30/2016 18:26:47",
		"visitDelegate:" : " 10/30/2016 18:26:47",
		"visitMapping:" : " 10/30/2016 18:26:47",
		"visitTrimming:" : " 10/30/2016 18:26:47",
		"context:" : " 10/30/2016 18:26:47",
		"visitLiteralObject:" : " 10/30/2016 18:26:47",
		"visitComposite:" : "JanKurs 11/4/2016 20:58",
		"visitWater:" : " 10/30/2016 18:26:47",
		"visitToken:" : "JanKurs 11/4/2016 20:59",
		"add:to:" : " 10/30/2016 18:26:47",
		"visitEpsilon:" : " 10/30/2016 18:26:47",
		"addAll:to:" : " 10/30/2016 18:26:47",
		"visitAction:" : "JanKurs 11/4/2016 20:58",
		"visitEnd:" : " 10/30/2016 18:26:47",
		"visitPop:" : "JanKurs 11/1/2016 17:34",
		"visitNot:" : "JanKurs 11/4/2016 20:59",
		"visitPredicateObject:" : " 10/30/2016 18:26:47",
		"visitLiteralSequence:" : " 10/30/2016 18:26:47",
		"visitChoice:" : " 10/30/2016 18:26:47",
		"visitEndOfInput:" : " 10/30/2016 18:26:47",
		"visitSea:" : "JanKurs 11/2/2016 15:47",
		"visitAnd:" : "JanKurs 11/4/2016 20:58"
	},
	"class" : { }
}